cicd/__init__.py
cicd/simple_cicd.py
onema_cdk.cicd_pipelines-0.0.10.dist-info/METADATA
onema_cdk.cicd_pipelines-0.0.10.dist-info/WHEEL
onema_cdk.cicd_pipelines-0.0.10.dist-info/top_level.txt
onema_cdk.cicd_pipelines-0.0.10.dist-info/RECORD
