Metadata-Version: 2.1
Name: onema-cdk.cicd-pipelines
Version: 0.0.10
Summary: Constructs to deploy CICD pipelines using CodePipeline and CodeBuild
Home-page: https://github.com/onema/cdk-constructs
Author: Juan Manuel Torres
Author-email: software@onema.io
License: UNKNOWN
Project-URL: Bug Tracker, https://github.com/onema/cdk-constructs/issues
Project-URL: Documentation, https://github.com/onema/cdk-constructs
Project-URL: Source Code, https://github.com/onema/cdk-constructs
Platform: UNKNOWN
Classifier: Development Status :: 4 - Beta
Classifier: Intended Audience :: Developers
Classifier: License :: OSI Approved :: Apache Software License
Classifier: Programming Language :: JavaScript
Classifier: Programming Language :: Python :: 3 :: Only
Classifier: Programming Language :: Python :: 3.6
Classifier: Programming Language :: Python :: 3.7
Classifier: Programming Language :: Python :: 3.8
Classifier: Topic :: Software Development :: Code Generators
Classifier: Topic :: Utilities
Classifier: Typing :: Typed
Requires-Python: >=3.6
Requires-Dist: aws-cdk.core
Requires-Dist: aws-cdk.aws-codebuild
Requires-Dist: aws-cdk.aws-codepipeline
Requires-Dist: aws-cdk.aws-codepipeline-actions
Requires-Dist: aws-cdk.aws-ssm
